sol_usb/__init__.py
sol_usb/cli.py
sol_usb/full_devices.py
sol_usb/py.typed
sol_usb/usb2.py
sol_usb/usb3.py
sol_usb/gateware/__init__.py
sol_usb/gateware/memory.py
sol_usb/gateware/applets/__init__.py
sol_usb/gateware/applets/analyzer.py
sol_usb/gateware/applets/dc_flash.py
sol_usb/gateware/applets/speed_test.py
sol_usb/gateware/architecture/__init__.py
sol_usb/gateware/architecture/car.py
sol_usb/gateware/debug/__init__.py
sol_usb/gateware/debug/console.py
sol_usb/gateware/debug/ila.py
sol_usb/gateware/interface/__init__.py
sol_usb/gateware/interface/flash.py
sol_usb/gateware/interface/jtag.py
sol_usb/gateware/interface/pipe.py
sol_usb/gateware/interface/psram.py
sol_usb/gateware/interface/spi.py
sol_usb/gateware/interface/uart.py
sol_usb/gateware/interface/ulpi.py
sol_usb/gateware/interface/utmi.py
sol_usb/gateware/interface/gateware_phy/__init__.py
sol_usb/gateware/interface/gateware_phy/phy.py
sol_usb/gateware/interface/gateware_phy/receiver.py
sol_usb/gateware/interface/gateware_phy/transmitter.py
sol_usb/gateware/interface/serdes_phy/__init__.py
sol_usb/gateware/interface/serdes_phy/ecp5.py
sol_usb/gateware/interface/serdes_phy/lfps.py
sol_usb/gateware/interface/serdes_phy/xc7.py
sol_usb/gateware/interface/serdes_phy/xc7_gtp.py
sol_usb/gateware/interface/serdes_phy/xc7_gtx.py
sol_usb/gateware/platform/__init__.py
sol_usb/gateware/platform/core.py
sol_usb/gateware/platform/luna_r0_1.py
sol_usb/gateware/platform/luna_r0_2.py
sol_usb/gateware/platform/luna_r0_3.py
sol_usb/gateware/platform/luna_r0_4.py
sol_usb/gateware/soc/__init__.py
sol_usb/gateware/soc/cpu.py
sol_usb/gateware/soc/memory.py
sol_usb/gateware/soc/peripheral.py
sol_usb/gateware/soc/simplesoc.py
sol_usb/gateware/soc/uart.py
sol_usb/gateware/stream/__init__.py
sol_usb/gateware/stream/arbiter.py
sol_usb/gateware/stream/generator.py
sol_usb/gateware/test/__init__.py
sol_usb/gateware/test/usb2.py
sol_usb/gateware/test/utils.py
sol_usb/gateware/test/contrib/__init__.py
sol_usb-0.8.0.dist-info/licenses/LICENSE.docs
sol_usb-0.8.0.dist-info/licenses/LICENSE.hardware
sol_usb-0.8.0.dist-info/licenses/LICENSE.software
sol_usb-0.8.0.dist-info/METADATA
sol_usb-0.8.0.dist-info/WHEEL
sol_usb-0.8.0.dist-info/top_level.txt
sol_usb-0.8.0.dist-info/zip-safe
sol_usb-0.8.0.dist-info/RECORD
